flowreg3d/__init__.py
flowreg3d/_runtime.py
flowreg3d/cli/__init__.py
flowreg3d/cli/concat_tiffs.py
flowreg3d/cli/main.py
flowreg3d/cli/tiff_reshape.py
flowreg3d/core/__init__.py
flowreg3d/core/level_solver_3d.py
flowreg3d/core/optical_flow_3d.py
flowreg3d/core/torch/__init__.py
flowreg3d/core/torch/level_solver_3d.py
flowreg3d/core/torch/optical_flow_3d.py
flowreg3d/motion_correction/OF_options_3D.py
flowreg3d/motion_correction/__init__.py
flowreg3d/motion_correction/compensate_arr_3D.py
flowreg3d/motion_correction/compensate_recording_3D.py
flowreg3d/motion_correction/parallelization/__init__.py
flowreg3d/motion_correction/parallelization/base_3d.py
flowreg3d/motion_correction/parallelization/multiprocessing_3d.py
flowreg3d/motion_correction/parallelization/sequential_3d.py
flowreg3d/motion_correction/parallelization/threading_3d.py
flowreg3d/motion_generation/__init__.py
flowreg3d/motion_generation/motion_generators.py
flowreg3d/util/__init__.py
flowreg3d/util/image_processing_3D.py
flowreg3d/util/random.py
flowreg3d/util/resize_util_3D.py
flowreg3d/util/xcorr_prealignment.py
flowreg3d/util/io/__init__.py
flowreg3d/util/io/_arr_3d.py
flowreg3d/util/io/_base.py
flowreg3d/util/io/_base_3d.py
flowreg3d/util/io/_ds_io_3d.py
flowreg3d/util/io/_scanimage.py
flowreg3d/util/io/factory.py
flowreg3d/util/io/hdf5_3d.py
flowreg3d/util/io/mat_3d.py
flowreg3d/util/io/multifile_wrappers_3d.py
flowreg3d/util/io/tiff.py
flowreg3d/util/io/tiff_3d.py
flowreg3d/util/torch/__init__.py
flowreg3d/util/torch/image_processing_3D.py
flowreg3d/util/torch/resize_util_3D.py
flowreg3d-0.0.0.dist-info/licenses/LICENSE.txt
flowreg3d-0.0.0.dist-info/METADATA
flowreg3d-0.0.0.dist-info/WHEEL
flowreg3d-0.0.0.dist-info/entry_points.txt
flowreg3d-0.0.0.dist-info/top_level.txt
flowreg3d-0.0.0.dist-info/RECORD
