Metadata-Version: 2.4
Name: flowreg3d
Version: 0.0.0
Summary: 3D Variational optical-flow motion estimation and correction for 2-photon microscopy 3D videos
Author-email: Philipp Flotho <Philipp.Flotho@uni-saarland.de>
Classifier: Development Status :: 3 - Alpha
Classifier: Intended Audience :: Science/Research
Classifier: License :: Other/Proprietary License
Classifier: Operating System :: OS Independent
Classifier: Programming Language :: Python :: 3
Classifier: Programming Language :: Python :: 3.10
Classifier: Programming Language :: Python :: 3.11
Classifier: Programming Language :: Python :: 3.12
Classifier: Programming Language :: Python :: 3.13
Classifier: Topic :: Scientific/Engineering :: Image Processing
Classifier: Topic :: Scientific/Engineering :: Bio-Informatics
Requires-Python: >=3.10
License-File: LICENSE.txt
Requires-Dist: numpy>=2.0.0
Requires-Dist: scipy>=1.14.0
Requires-Dist: scikit-image>=0.24.0
Requires-Dist: opencv-contrib-python>=4.10.0
Requires-Dist: h5py>=3.12.0
Requires-Dist: tifffile>=2024.9.0
Requires-Dist: numba>=0.60.0
Requires-Dist: pydantic<3.0.0,>=2.11.0
Requires-Dist: hdf5storage>=0.2.0
Provides-Extra: vis
Requires-Dist: matplotlib>=3.8.0; extra == "vis"
Requires-Dist: scikit-learn>=1.5.0; extra == "vis"
Requires-Dist: napari[all]; extra == "vis"
Provides-Extra: test
Requires-Dist: pytest>=8.0.0; extra == "test"
Requires-Dist: pytest-cov>=5.0.0; extra == "test"
Provides-Extra: gpu
Requires-Dist: torch>=2.2.0; extra == "gpu"
Dynamic: license-file
